{
  "data": [
    {
      "name": "0",
      "dimension": "acct_quotas",
      "dimension_id": "eventingress",
      "dimension_type": "size",
      "aggregation": "sum",
      "values": [
        {
          "value": 3098,
          "ts": "1673769600000"
        },
        {
          "value": 2953,
          "ts": "1673856000000"
        },
        {
          "value": 3043,
          "ts": "1673942400000"
        },
        {
          "value": 3019,
          "ts": "1674028800000"
        },
        {
          "value": 3167,
          "ts": "1674115200000"
        },
        {
          "value": 3074,
          "ts": "1674201600000"
        },
        {
          "value": 3034,
          "ts": "1674288000000"
        },
        {
          "value": 3050,
          "ts": "1674374400000"
        },
        {
          "value": 3129,
          "ts": "1674460800000"
        },
        {
          "value": 3054,
          "ts": "1674547200000"
        },
        {
          "value": 3103,
          "ts": "1674633600000"
        },
        {
          "value": 2970,
          "ts": "1674720000000"
        },
        {
          "value": 3017,
          "ts": "1674806400000"
        },
        {
          "value": 3056,
          "ts": "1674892800000"
        },
        {
          "value": 3056,
          "ts": "1674979200000"
        },
        {
          "value": 2958,
          "ts": "1675065600000"
        },
        {
          "value": 3206,
          "ts": "1675152000000"
        },
        {
          "value": 2878,
          "ts": "1675238400000"
        },
        {
          "value": 3202,
          "ts": "1675324800000"
        },
        {
          "value": 2993,
          "ts": "1675411200000"
        },
        {
          "value": 2996,
          "ts": "1675497600000"
        },
        {
          "value": 3014,
          "ts": "1675584000000"
        },
        {
          "value": 3065,
          "ts": "1675670400000"
        },
        {
          "value": 3015,
          "ts": "1675756800000"
        },
        {
          "value": 3028,
          "ts": "1675843200000"
        },
        {
          "value": 2894,
          "ts": "1675929600000"
        },
        {
          "value": 3220,
          "ts": "1676016000000"
        },
        {
          "value": 3054,
          "ts": "1676102400000"
        },
        {
          "value": 3111,
          "ts": "1676188800000"
        },
        {
          "value": 3032,
          "ts": "1676275200000"
        },
        {
          "value": 3090,
          "ts": "1676361600000"
        },
        {
          "value": 3044,
          "ts": "1676448000000"
        },
        {
          "value": 2937,
          "ts": "1676534400000"
        },
        {
          "value": 3138,
          "ts": "1676620800000"
        },
        {
          "value": 2903,
          "ts": "1676707200000"
        },
        {
          "value": 3147,
          "ts": "1676793600000"
        },
        {
          "value": 2841,
          "ts": "1676880000000"
        },
        {
          "value": 3288,
          "ts": "1676966400000"
        },
        {
          "value": 3011,
          "ts": "1677052800000"
        },
        {
          "value": 3016,
          "ts": "1677139200000"
        },
        {
          "value": 3033,
          "ts": "1677225600000"
        },
        {
          "value": 3086,
          "ts": "1677312000000"
        },
        {
          "value": 3049,
          "ts": "1677398400000"
        },
        {
          "value": 3054,
          "ts": "1677484800000"
        },
        {
          "value": 2994,
          "ts": "1677571200000"
        },
        {
          "value": 3081,
          "ts": "1677657600000"
        },
        {
          "value": 3053,
          "ts": "1677744000000"
        },
        {
          "value": 2984,
          "ts": "1677830400000"
        },
        {
          "value": 2956,
          "ts": "1677916800000"
        },
        {
          "value": 3157,
          "ts": "1678003200000"
        },
        {
          "value": 2924,
          "ts": "1678089600000"
        },
        {
          "value": 3233,
          "ts": "1678176000000"
        },
        {
          "value": 3031,
          "ts": "1678262400000"
        },
        {
          "value": 2952,
          "ts": "1678348800000"
        },
        {
          "value": 2967,
          "ts": "1678435200000"
        },
        {
          "value": 2913,
          "ts": "1678521600000"
        },
        {
          "value": 3072,
          "ts": "1678608000000"
        },
        {
          "value": 2974,
          "ts": "1678694400000"
        },
        {
          "value": 2996,
          "ts": "1678780800000"
        },
        {
          "value": 2947,
          "ts": "1678867200000"
        },
        {
          "value": 3063,
          "ts": "1678953600000"
        },
        {
          "value": 2988,
          "ts": "1679040000000"
        },
        {
          "value": 2849,
          "ts": "1679126400000"
        },
        {
          "value": 2996,
          "ts": "1679212800000"
        },
        {
          "value": 3160,
          "ts": "1679299200000"
        },
        {
          "value": 2944,
          "ts": "1679385600000"
        },
        {
          "value": 3036,
          "ts": "1679472000000"
        },
        {
          "value": 2994,
          "ts": "1679558400000"
        },
        {
          "value": 1499,
          "ts": "1679644800000"
        }
      ]
    },
    {
      "name": "1",
      "dimension": "acct_quotas",
      "dimension_id": "eventingress",
      "dimension_type": "size",
      "aggregation": "sum",
      "values": [
        {
          "value": 207889,
          "ts": "1673769600000"
        }
      ],
      "sum": 207889
    }
  ],
  "message": "success",
  "status": 200
}
